ssh_from_env/main.py
ssh_from_env-0.0.0.dist-info/METADATA
ssh_from_env-0.0.0.dist-info/WHEEL
ssh_from_env-0.0.0.dist-info/entry_points.txt
ssh_from_env-0.0.0.dist-info/licenses/LICENSE
ssh_from_env-0.0.0.dist-info/RECORD
