Metadata-Version: 2.3
Name: ssh_from_env
Version: 0.0.0
Summary: With private keys stored as environment variables, create a basic SSH interactive session with Fabric. 
Project-URL: Homepage, https://github.com/JamesParrott/ssh_from_env
Project-URL: Bug Tracker, https://github.com/JamesParrott/ssh_from_env/issues
Author-email: James Parrott <james.parrott@proton.me>
License: Copyright 2024 James Parrott
License-File: LICENSE
Keywords: SSH
Classifier: Programming Language :: Python
Requires-Python: >=3.6
Requires-Dist: fabric
